CHANGES.txt
LICENSE.txt
MANIFEST.in
README.rst
REQUIREMENTS.txt
setup.cfg
setup.py
GoogleToken/Configuration.py
GoogleToken/Crypto.py
GoogleToken/Generator.py
GoogleToken/Main.py
GoogleToken/Phantom.py
GoogleToken/Utils.py
GoogleToken/__init__.py
GoogleToken.egg-info/PKG-INFO
GoogleToken.egg-info/SOURCES.txt
GoogleToken.egg-info/dependency_links.txt
GoogleToken.egg-info/requires.txt
GoogleToken.egg-info/top_level.txt