Metadata-Version: 1.1
Name: GoogleToken
Version: 0.7.6
Summary: Google User Account login automation
Home-page: http://github.com/scottphilip/google-token
Author: Scott Philip
Author-email: sp@scottphilip.com
License: GNU (v3) License
Keywords: Google Account,Access Token,oauth2,Automation
Platform: UNKNOWN
Classifier: Environment :: Web Environment
Classifier: Intended Audience :: Developers
Classifier: Operating System :: OS Independent
Classifier: Programming Language :: Python
Classifier: Programming Language :: Python :: 2.7
Classifier: Programming Language :: Python :: 3.3
Classifier: Programming Language :: Python :: 3.4
Classifier: Programming Language :: Python :: 3.5
Classifier: Programming Language :: Python :: 3.6
